{"id":"mystic-intellect-commander-2019","name":"Mystic Intellect","set":"Commander 2019","cards":[{"quantity":1,"name":"Azorius Chancery","setCode":"c19","collectorNumber":"228","scryfallId":"541776bb-8643-4742-873b-8bf211d6ee99","commander":false},{"quantity":1,"name":"Ash Barrens","setCode":"c19","collectorNumber":"227","scryfallId":"d78e34c2-6a1e-4559-9b3f-ac45d330d515","commander":false},{"quantity":1,"name":"Armillary Sphere","setCode":"c19","collectorNumber":"209","scryfallId":"5021f5e0-1fd9-4b2c-a3b7-b35ce6f5b5ba","commander":false},{"quantity":1,"name":"Azorius Locket","setCode":"c19","collectorNumber":"210","scryfallId":"6cdb0b3a-cf96-40d1-b3d2-2d87f6763097","commander":false},{"quantity":1,"name":"Backdraft Hellkite","setCode":"c19","collectorNumber":"23","scryfallId":"2af9027d-c1d2-49b6-b303-04e37d38e010","commander":false},{"quantity":1,"name":"Bloodthirsty Blade","setCode":"c19","collectorNumber":"53","scryfallId":"42ceb92a-2f41-43d2-884b-b3362d611cfd","commander":false},{"quantity":1,"name":"Boros Garrison","setCode":"c19","collectorNumber":"233","scryfallId":"a4a3a23c-544d-4ed4-90ad-dbf04f676af3","commander":false},{"quantity":1,"name":"Boros Guildgate","setCode":"c19","collectorNumber":"234","scryfallId":"28d6c68f-5e41-4b10-b4fa-8f7aee6b587b","commander":false},{"quantity":1,"name":"Burnished Hart","setCode":"c19","collectorNumber":"211","scryfallId":"cc80010d-f02a-4bd2-a36a-d17abbe922a0","commander":false},{"quantity":1,"name":"Clever Impersonator","setCode":"c19","collectorNumber":"82","scryfallId":"c0516453-3e6a-4b7f-8df6-72a6e207169a","commander":false},{"quantity":1,"name":"Burning Vengeance","setCode":"c19","collectorNumber":"135","scryfallId":"dbbfdc21-d8a0-4666-94e6-76b3fa083e76","commander":false},{"quantity":1,"name":"Cliffside Rescuer","setCode":"c19","collectorNumber":"1","scryfallId":"c998d2ba-d2ca-4a85-b22a-ce8f42bb0d2f","commander":false},{"quantity":1,"name":"Chemister's Insight","setCode":"c19","collectorNumber":"80","scryfallId":"caef3c0e-cb28-464a-8a50-ce149c06a01e","commander":false},{"quantity":1,"name":"Commander's Sphere","setCode":"c19","collectorNumber":"212","scryfallId":"6a628aff-7db5-4df9-9c3d-c58b0d7232a6","commander":false},{"quantity":1,"name":"Command Tower","setCode":"c19","collectorNumber":"237","scryfallId":"c328d8ac-97df-4240-ac38-7cab363c5da1","commander":false},{"quantity":1,"name":"Deep Analysis","setCode":"c19","collectorNumber":"83","scryfallId":"7a7a6d2d-be31-474b-811d-3802e32f3768","commander":false},{"quantity":1,"name":"Desperate Ravings","setCode":"c19","collectorNumber":"137","scryfallId":"b2e59ba7-e4e1-4c51-a34c-17a48850a0f5","commander":false},{"quantity":1,"name":"Devil's Play","setCode":"c19","collectorNumber":"138","scryfallId":"d46473a7-69f5-492b-845d-c8862a1fec85","commander":false},{"quantity":1,"name":"Crackling Drake","setCode":"c19","collectorNumber":"190","scryfallId":"c8b9fe6c-4efb-4840-9d1a-40203c96efa2","commander":false},{"quantity":1,"name":"Dockside Extortionist","setCode":"c19","collectorNumber":"24","scryfallId":"571bc9eb-8d13-4008-86b5-2e348a326d58","commander":false},{"quantity":1,"name":"Divine Reckoning","setCode":"c19","collectorNumber":"62","scryfallId":"cbb97027-d6bc-4529-960d-6b0ab2af9c50","commander":false},{"quantity":1,"name":"Exotic Orchard","setCode":"c19","collectorNumber":"242","scryfallId":"23de2dc2-348f-4eeb-ae0c-dda422d654b0","commander":false},{"quantity":1,"name":"Fact or Fiction","setCode":"c19","collectorNumber":"85","scryfallId":"d7a7a247-51bd-4244-81c7-2b406a23cc69","commander":false},{"quantity":1,"name":"Faithless Looting","setCode":"c19","collectorNumber":"140","scryfallId":"dbf7f017-17a4-403e-8a8c-c76e36d55d9f","commander":false},{"quantity":1,"name":"Evolving Wilds","setCode":"c19","collectorNumber":"241","scryfallId":"b6f4f0c7-63c8-4d43-9ccb-920733980de0","commander":false},{"quantity":1,"name":"Dusk // Dawn","setCode":"c19","collectorNumber":"63","scryfallId":"e9d5aee0-5963-41db-a22b-cfea40a967a3","commander":false},{"quantity":1,"name":"Empowered Autogenerator","setCode":"c19","collectorNumber":"54","scryfallId":"2c9b8d53-97c9-4e3d-a8c6-6abd78db6390","commander":false},{"quantity":1,"name":"Fervent Denial","setCode":"c19","collectorNumber":"86","scryfallId":"7b15428e-946e-490d-93bb-9888bfd3a1df","commander":false},{"quantity":1,"name":"Farm // Market","setCode":"c19","collectorNumber":"192","scryfallId":"fe3b32dc-f7e6-455c-b9d1-c7f8d6259179","commander":false},{"quantity":1,"name":"Gerrard, Weatherlight Hero","setCode":"c19","collectorNumber":"41","scryfallId":"c835a37a-776a-44ef-a252-4af1f31bf0b3","commander":false},{"quantity":1,"name":"Ghostly Prison","setCode":"c19","collectorNumber":"64","scryfallId":"daeca212-3a70-470e-a934-9cd7e0ebf7eb","commander":false},{"quantity":1,"name":"Guttersnipe","setCode":"c19","collectorNumber":"145","scryfallId":"7ed62dc1-4e78-423c-b9d3-def3b7e95c71","commander":false},{"quantity":1,"name":"Highland Lake","setCode":"c19","collectorNumber":"251","scryfallId":"46bb20af-a326-4a42-94d3-cb1990300e0f","commander":false},{"quantity":1,"name":"Ignite the Future","setCode":"c19","collectorNumber":"27","scryfallId":"5a9472e0-1a6d-47f7-91eb-9bdb000e1f1b","commander":false},{"quantity":1,"name":"Increasing Vengeance","setCode":"c19","collectorNumber":"147","scryfallId":"2a362d78-76a1-4dbc-80cc-0360e98ba280","commander":false},{"quantity":1,"name":"Increasing Devotion","setCode":"c19","collectorNumber":"66","scryfallId":"996e9d99-d569-4bf1-893e-24b4f90d31aa","commander":false},{"quantity":1,"name":"Izzet Boilerworks","setCode":"c19","collectorNumber":"252","scryfallId":"5aec82af-b223-4003-ab7f-7e40a81e0842","commander":false},{"quantity":1,"name":"Izzet Guildgate","setCode":"c19","collectorNumber":"253","scryfallId":"c60c576b-a1ea-41d2-a1d8-4417c11ed48e","commander":false},{"quantity":1,"name":"Jace's Sanctum","setCode":"c19","collectorNumber":"88","scryfallId":"8148adc6-7946-4abd-8601-b1f4cd6916c2","commander":false},{"quantity":1,"name":"Izzet Locket","setCode":"c19","collectorNumber":"215","scryfallId":"a32ecc71-b924-4414-94ee-c6cb0ba752e5","commander":false},{"quantity":1,"name":"Magmaquake","setCode":"c19","collectorNumber":"148","scryfallId":"110773d4-d444-4d30-8715-a433185c7167","commander":false},{"quantity":1,"name":"Leadership Vacuum","setCode":"c19","collectorNumber":"9","scryfallId":"4fa953a9-171c-4532-a352-40ce27eed3c4","commander":false},{"quantity":1,"name":"Mandate of Peace","setCode":"c19","collectorNumber":"4","scryfallId":"d243055f-892e-4042-9694-13d5e99e3550","commander":false},{"quantity":1,"name":"Mass Diminish","setCode":"c19","collectorNumber":"10","scryfallId":"762a0e40-af3c-4ef9-a9fc-0414a1758385","commander":false},{"quantity":1,"name":"Myriad Landscape","setCode":"c19","collectorNumber":"261","scryfallId":"3a1c15b9-8039-4de3-a060-d1c38f9e5518","commander":false},{"quantity":1,"name":"Mystic Monastery","setCode":"c19","collectorNumber":"262","scryfallId":"35978c6a-6d36-452a-a3c5-cf4f3a11263f","commander":false},{"quantity":1,"name":"Mystic Retrieval","setCode":"c19","collectorNumber":"90","scryfallId":"0cea3484-889b-492d-a6d3-d4b95ed5df6e","commander":false},{"quantity":1,"name":"Oona's Grace","setCode":"c19","collectorNumber":"91","scryfallId":"e2128105-de04-4f51-81c7-37f30cf324d4","commander":false},{"quantity":1,"name":"Prismatic Strands","setCode":"c19","collectorNumber":"69","scryfallId":"efd85985-abc1-430a-9210-63109c90a82d","commander":false},{"quantity":1,"name":"Prairie Stream","setCode":"c19","collectorNumber":"265","scryfallId":"beaf2d9d-f25c-46d9-940d-b4c3287a5a74","commander":false},{"quantity":1,"name":"Purify the Grave","setCode":"c19","collectorNumber":"71","scryfallId":"dc396f54-8f54-4456-b473-a9bb38e88f62","commander":false},{"quantity":1,"name":"Pristine Skywise","setCode":"c19","collectorNumber":"196","scryfallId":"516512f5-b4ce-46d3-bdda-c88b357192ca","commander":false},{"quantity":1,"name":"Pristine Angel","setCode":"c19","collectorNumber":"70","scryfallId":"2fbd3a6b-831d-4876-9f84-861cab788747","commander":false},{"quantity":1,"name":"Refuse // Cooperate","setCode":"c19","collectorNumber":"199","scryfallId":"ca4caa4e-6b8f-4be8-b177-de2ebe2c9201","commander":false},{"quantity":1,"name":"Ral Zarek","setCode":"c19","collectorNumber":"198","scryfallId":"5639a7a6-8155-44b6-b22f-4596581002c3","commander":false},{"quantity":1,"name":"Ray of Distortion","setCode":"c19","collectorNumber":"72","scryfallId":"ba1af997-bf99-4330-b24d-368615107ebc","commander":false},{"quantity":1,"name":"River Kelpie","setCode":"c19","collectorNumber":"93","scryfallId":"81efe7cf-81f0-4799-813f-73ec8d865190","commander":false},{"quantity":1,"name":"Runic Repetition","setCode":"c19","collectorNumber":"94","scryfallId":"8cabd32b-187d-4a41-92b2-72c3b3216728","commander":false},{"quantity":1,"name":"Rolling Temblor","setCode":"c19","collectorNumber":"151","scryfallId":"2a1ec927-b645-4285-8765-02c0ac104ae1","commander":false},{"quantity":1,"name":"Scaretiller","setCode":"c19","collectorNumber":"57","scryfallId":"7729fb41-3025-4e7b-8cf3-003fdc10300b","commander":false},{"quantity":1,"name":"Secrets of the Dead","setCode":"c19","collectorNumber":"95","scryfallId":"066311f5-51fc-4da9-a5fa-fa5059a88e5b","commander":false},{"quantity":1,"name":"Sevinne's Reclamation","setCode":"c19","collectorNumber":"5","scryfallId":"7e68f4df-88ce-4e09-a03c-7edf40bff167","commander":false},{"quantity":1,"name":"Sol Ring","setCode":"c19","collectorNumber":"221","scryfallId":"e672d408-997c-4a19-810a-3da8411eecf2","commander":false},{"quantity":1,"name":"Storm Herd","setCode":"c19","collectorNumber":"75","scryfallId":"058a7abf-8112-4f67-b465-317c87ad0d63","commander":false},{"quantity":1,"name":"Stone Quarry","setCode":"c19","collectorNumber":"276","scryfallId":"3c64d130-2864-4e1e-9024-58821eec3be5","commander":false},{"quantity":1,"name":"Sun Titan","setCode":"c19","collectorNumber":"76","scryfallId":"3ccf318d-5ca5-4e4c-a78a-206a815f9381","commander":false},{"quantity":1,"name":"Swiftwater Cliffs","setCode":"c19","collectorNumber":"279","scryfallId":"2a6f4398-51f3-4f73-802a-9528e0c86061","commander":false},{"quantity":1,"name":"Temple of the False God","setCode":"c19","collectorNumber":"280","scryfallId":"22c66095-ee5d-4258-8e24-78e81b64a519","commander":false},{"quantity":1,"name":"Talrand, Sky Summoner","setCode":"c19","collectorNumber":"97","scryfallId":"abe8b487-b188-44c2-adba-141516b90849","commander":false},{"quantity":1,"name":"Terramorphic Expanse","setCode":"c19","collectorNumber":"281","scryfallId":"9acbdb64-fa26-4c77-b513-33e44ac86e20","commander":false},{"quantity":1,"name":"Thalia's Geistcaller","setCode":"c19","collectorNumber":"7","scryfallId":"4531482d-9238-40de-957e-61beb5700330","commander":false},{"quantity":1,"name":"Tranquil Cove","setCode":"c19","collectorNumber":"284","scryfallId":"36c70a1d-c129-4c97-a190-6b3eaa83d48c","commander":false},{"quantity":1,"name":"Think Twice","setCode":"c19","collectorNumber":"99","scryfallId":"7b93726a-9ee7-4010-9db1-1e1ac5955398","commander":false},{"quantity":1,"name":"Wind-Scarred Crag","setCode":"c19","collectorNumber":"285","scryfallId":"23c33230-d9bb-4cdc-913b-fa5ee64ee8cd","commander":false},{"quantity":1,"name":"Wall of Stolen Identity","setCode":"c19","collectorNumber":"13","scryfallId":"359cc32c-ba90-43e0-b584-09efd321a672","commander":false},{"quantity":1,"name":"Zetalpa, Primal Dawn","setCode":"c19","collectorNumber":"79","scryfallId":"f557ebfc-6fa2-4512-9d46-b6a2b0464eeb","commander":false},{"quantity":1,"name":"Elsha of the Infinite","setCode":"c19","collectorNumber":"40","scryfallId":"3b977c0b-07a1-4d16-9fdd-fc0563e0b68e","commander":false},{"quantity":1,"name":"Pramikon, Sky Rampart","setCode":"c19","collectorNumber":"47","scryfallId":"8569ad47-a243-402d-899f-4e6b17ea4e1e","commander":false},{"quantity":8,"name":"Island","setCode":"c19","collectorNumber":"292","scryfallId":"8cf9b48e-cf58-43a9-94ff-2d50846c3386","commander":false},{"quantity":4,"name":"Mountain","setCode":"c19","collectorNumber":"297","scryfallId":"db6d3fb9-ecec-4a55-bfcf-6ae2d35e416a","commander":false},{"quantity":9,"name":"Plains","setCode":"c19","collectorNumber":"288","scryfallId":"247d1875-b59d-475c-926f-0ecf4e7c0faf","commander":false},{"quantity":1,"name":"Sevinne, the Chronoclasm","setCode":"c19","collectorNumber":"49","scryfallId":"2c209efe-b4dc-44a3-bd45-d647f5680cbe","commander":true}]}